{
  "_mismatches": [],
  "_needs_review": [],
  "_notes_source": "",
  "audit_version": 1,
  "audited_at": "2026-05-11T16:56:26Z",
  "audited_by": "audit-package.py",
  "blfs": {
    "anchor_id": "docutils",
    "blfs_name": "docutils",
    "blfs_version": "0.22.4",
    "deps": [],
    "patches": []
  },
  "build_system": "python",
  "bundled_libs": [],
  "docs_seen": [
    "HACKING",
    "README",
    "TODO"
  ],
  "expected_binaries": [
    "docutils",
    "rst2html4",
    "rst2html5",
    "rst2html",
    "rst2latex",
    "rst2man",
    "rst2odt",
    "rst2pseudoxml",
    "rst2s5",
    "rst2xetex",
    "rst2xml",
    "doxypypy",
    "doxyqml",
    "gi-docgen",
    "mako-render",
    "f2py",
    "f2py3",
    "f2py3.14 (3 copies of the same script)",
    "pygmentize",
    "pyserial-miniterm",
    "pyserial-ports",
    "pytest",
    "py.test (different files but with same content)",
    "cm2html",
    "cm2latex",
    "cm2man",
    "cm2pseudoxml",
    "cm2xetex",
    "cm2xml",
    "scour",
    "sphinx-apidoc",
    "sphinx-autogen",
    "sphinx-build",
    "sphinx-quickstart"
  ],
  "expected_headers": [],
  "expected_libs": [
    "/usr/lib/python3.14/site-packages/gi/_gi{",
    "_cairo}.cpython-314-&lt;arch&gt;-linux-gnu.so"
  ],
  "expected_pkgconfig": [],
  "name": "docutils",
  "our_autotools_flags": [
    "--no-build-isolation",
    "--no-cache-dir",
    "--no-deps"
  ],
  "our_deps_build": [
    "docbook-xsl-nons"
  ],
  "our_deps_host": [],
  "our_deps_runtime": [],
  "our_meson_options": [],
  "our_patches": [],
  "package_dir": "packages/core/docutils",
  "reproducibility": {
    "_notes": "auto-derived by agent-c01",
    "deterministic_install": 1,
    "parallel_build_supported": null,
    "source_date_epoch_supported": 0
  },
  "source_sha256": "4db53b1fde9abecbb74d91230d32ab626d94f6badfc575d6db9194a49df29968",
  "source_tarball": "docutils-0.22.4.tar.gz",
  "source_tarball_exists": true,
  "source_url": "https://files.pythonhosted.org/packages/source/d/docutils/docutils-${version}.tar.gz",
  "tarball_files_count": 769,
  "test_command": "pytest",
  "test_known_failures": [],
  "tier": "core",
  "upstream_options": [],
  "version": "0.22.4"
}
